{"aliases": ["2MASXJ12142972+2825243", "CGCG158-050", "LGG276:[G93]007", "MCG+05-29-040", "NGC4196", "PGC039098", "SDSSJ121429.74+282524.3", "SDSSJ121429.74+282524.4", "SDSSJ121429.75+282524.3", "SDSSJ121429.75+282524.4", "UGC07245", "[KG2002]J121429.75+282524.6", "UZC121154+28420"], "dec": ["+", "28", "25", "24.8"], "dec_float": 28.423555555555556, "name": "NGC 4196", "ra": ["12", "14", "29.76"], "ra_float": 12.2416, "values": {"a21": {"description": "21-cm self absorption", "text": "0.03", "unit": "mag", "value": 0.03}, "ag": {"description": "Galactic extinction in B-band", "text": "0.09", "unit": "mag", "value": 0.09}, "ai": {"description": "Internal extinction due to inclination in B-band", "text": "0.00", "unit": "mag", "value": 0.0}, "bri25": {"description": "Mean surface brightness within isophote 25 ", "text": "22.63", "unit": "mag/arcsec2", "value": 22.63}, "brief": {"description": "Mean effective surface brightness", "text": "20.76 ± 0.26", "unit": "mag/arcsec2", "value": [20.76, 0.26]}, "bt": {"description": "Total B-magnitude", "text": "13.62 ± 0.27", "unit": "mag", "value": [13.62, 0.27]}, "btc": {"description": "Total apparent corrected B-magnitude", "text": "13.48", "unit": "mag", "value": 13.48}, "grp_cz": {"description": "", "text": "3996.47", "unit": "", "value": 3996.47}, "grp_dec": {"description": "", "text": "29.31618", "unit": "", "value": 29.31618}, "grp_n": {"description": "", "text": "49", "unit": "", "value": 49.0}, "grp_ra": {"description": "", "text": "182.1227", "unit": "", "value": 182.1227}, "grp_rad": {"description": "", "text": "2.16544", "unit": "", "value": 2.16544}, "grp_sigma": {"description": "", "text": "174.587", "unit": "", "value": 174.587}, "incl": {"description": "Inclination between line of sight and polar axis of a galaxy", "text": "53.5", "unit": "deg", "value": 53.5}, "it": {"description": "Total I-magnitude", "text": "12.30 ± 0.10", "unit": "mag", "value": [12.3, 0.1]}, "itc": {"description": "Total apparent corrected I-magnitude", "text": "12.27", "unit": "mag", "value": 12.27}, "kt": {"description": "Total K-magnitude", "text": "9.89 ± 0.05", "unit": "mag", "value": [9.89, 0.05]}, "logd25": {"description": "log of apparent diameter (d25 in 0.1 arcmin)", "text": "1.06 ± 0.05", "unit": "log(0.1 arcmin)", "value": [1.06, 0.05]}, "logdc": {"description": "log of apparent corrected diameter (dc in 0.1 arcmin)", "text": "1.06", "unit": "log(0.1 arcmin)", "value": 1.06}, "logr25": {"description": "log of axis ratio (major axis/minor axis)", "text": "0.15 ± 0.03", "unit": "log", "value": [0.15, 0.03]}, "mabs": {"description": "Absolute B-band magnitude", "text": "-20.41 ± 0.379", "unit": "mag", "value": [-20.41, 0.379]}, "modbest": {"description": "Best distance modulus, combining mod0 and modz", "text": "33.89 ± 0.26", "unit": "mag", "value": [33.89, 0.26]}, "modz": {"description": "Cosmological distance modulus (from vvir with ΛCDM)", "text": "33.89 ± 0.26", "unit": "mag", "value": [33.89, 0.26]}, "objtype": {"description": "Type of object (G=galaxy; S=Star ...)", "text": "G", "unit": "", "value": "G  "}, "pa": {"description": "Major axis position angle (North Eastwards)", "text": "58.7", "unit": "deg", "value": 58.7}, "t": {"description": "Morphological type code", "text": "-2.0 ± 0.5", "unit": "", "value": [-2.0, 0.5]}, "type": {"description": "Morphological type", "text": "S0", "unit": "", "value": "S0   "}, "ut": {"description": "Total U-magnitude", "text": "15.19 ± 0.12", "unit": "mag", "value": [15.19, 0.12]}, "v": {"description": "Mean Heliocentric radial velocity (cz)", "text": "3946 ± 2", "unit": "km/s", "value": [3946, 2]}, "v3k": {"description": "Radial velocity (cz) with respect to the CMB radiation", "text": "4236 ± 2", "unit": "km/s", "value": [4236, 2]}, "vgsr": {"description": "Radial velocity (cz) with respect to the GSR", "text": "3939 ± 2", "unit": "km/s", "value": [3939, 2]}, "vlg": {"description": "Radial velocity (cz) with respect to the Local Group", "text": "3910 ± 2", "unit": "km/s", "value": [3910, 2]}, "vvir": {"description": "Radial velocity (cz) corrected for LG infall onto Virgo", "text": "4108 ± 2", "unit": "km/s", "value": [4108, 2]}}}