{"aliases": ["NGC5189"], "dec": ["-", "65", "58", "25.3"], "dec_float": -65.97369444444445, "name": "NGC 5189", "ra": ["13", "33", "32.90"], "ra_float": 13.55913888888889, "values": {"a21": {"description": "21-cm self absorption", "text": "0.02", "unit": "mag", "value": 0.02}, "ag": {"description": "Galactic extinction in B-band", "text": "4.47", "unit": "mag", "value": 4.47}, "bri25": {"description": "Mean surface brightness within isophote 25 ", "text": "20.88", "unit": "mag/arcsec2", "value": 20.88}, "bt": {"description": "Total B-magnitude", "text": "10.30 ± 0.50", "unit": "mag", "value": [10.3, 0.5]}, "btc": {"description": "Total apparent corrected B-magnitude", "text": "5.83", "unit": "mag", "value": 5.83}, "incl": {"description": "Inclination between line of sight and polar axis of a galaxy", "text": "0.0", "unit": "deg", "value": 0.0}, "logd25": {"description": "log of apparent diameter (d25 in 0.1 arcmin)", "text": "1.37 ± 0.09", "unit": "log(0.1 arcmin)", "value": [1.37, 0.09]}, "logr25": {"description": "log of axis ratio (major axis/minor axis)", "text": "0.00 ± 0.10", "unit": "log", "value": [0.0, 0.1]}, "objtype": {"description": "Type of object (G=galaxy; S=Star ...)", "text": "p", "unit": "", "value": "p  "}}}