{"aliases": ["2MASXJ12465474-1138133", "6dFJ1246548-113814", "IRAS12443-1121", "LGG304:[G93]005", "MCG-02-33-007", "NGC4680", "PGC043118", "PGC963465"], "dec": ["-", "11", "38", "13.3"], "dec_float": -11.637027777777778, "name": "NGC 4680", "ra": ["12", "46", "54.76"], "ra_float": 12.781877777777778, "values": {"a21": {"description": "21-cm self absorption", "text": "0.04", "unit": "mag", "value": 0.04}, "ag": {"description": "Galactic extinction in B-band", "text": "0.19", "unit": "mag", "value": 0.19}, "ai": {"description": "Internal extinction due to inclination in B-band", "text": "0.15", "unit": "mag", "value": 0.15}, "bar": {"description": "Barred galaxy (B)", "text": "B", "unit": "", "value": "B"}, "bri25": {"description": "Mean surface brightness within isophote 25 ", "text": "22.45", "unit": "mag/arcsec2", "value": 22.45}, "brief": {"description": "Mean effective surface brightness", "text": "21.50 ± 0.39", "unit": "mag/arcsec2", "value": [21.5, 0.39]}, "bt": {"description": "Total B-magnitude", "text": "13.23 ± 0.50", "unit": "mag", "value": [13.23, 0.5]}, "btc": {"description": "Total apparent corrected B-magnitude", "text": "12.85", "unit": "mag", "value": 12.85}, "grp_cz": {"description": "", "text": "2485.55", "unit": "", "value": 2485.55}, "grp_dec": {"description": "", "text": "-9.852818", "unit": "", "value": -9.852818}, "grp_n": {"description": "", "text": "13", "unit": "", "value": 13.0}, "grp_ra": {"description": "", "text": "191.5943", "unit": "", "value": 191.5943}, "grp_rad": {"description": "", "text": "2.93997", "unit": "", "value": 2.93997}, "grp_sigma": {"description": "", "text": "263.075", "unit": "", "value": 263.075}, "hic": {"description": "21-cm index btc-m21c in magnitude", "text": "3.53", "unit": "mag", "value": 3.53}, "incl": {"description": "Inclination between line of sight and polar axis of a galaxy", "text": "62.8", "unit": "deg", "value": 62.8}, "it": {"description": "Total I-magnitude", "text": "11.47 ± 0.08", "unit": "mag", "value": [11.47, 0.08]}, "itc": {"description": "Total apparent corrected I-magnitude", "text": "11.39", "unit": "mag", "value": 11.39}, "kt": {"description": "Total K-magnitude", "text": "9.78 ± 0.03", "unit": "mag", "value": [9.78, 0.03]}, "logd25": {"description": "log of apparent diameter (d25 in 0.1 arcmin)", "text": "1.13 ± 0.03", "unit": "log(0.1 arcmin)", "value": [1.13, 0.03]}, "logdc": {"description": "log of apparent corrected diameter (dc in 0.1 arcmin)", "text": "1.14", "unit": "log(0.1 arcmin)", "value": 1.14}, "logr25": {"description": "log of axis ratio (major axis/minor axis)", "text": "0.25 ± 0.04", "unit": "log", "value": [0.25, 0.04]}, "m21": {"description": "21-cm line flux in magnitude", "text": "16.42 ± 0.28", "unit": "mag", "value": [16.42, 0.28]}, "m21c": {"description": "Corrected 21-cm line flux in magnitude", "text": "16.38", "unit": "mag", "value": 16.38}, "mabs": {"description": "Absolute B-band magnitude", "text": "-20.05 ± 0.501", "unit": "mag", "value": [-20.05, 0.501]}, "mod0": {"description": "Distance modulus from distance measurements", "text": "32.90 ± 0.03", "unit": "mag", "value": [32.9, 0.03]}, "modbest": {"description": "Best distance modulus, combining mod0 and modz", "text": "32.90 ± 0.03", "unit": "mag", "value": [32.9, 0.03]}, "modz": {"description": "Cosmological distance modulus (from vvir with ΛCDM)", "text": "32.77 ± 0.44", "unit": "mag", "value": [32.77, 0.44]}, "objtype": {"description": "Type of object (G=galaxy; S=Star ...)", "text": "G", "unit": "", "value": "G  "}, "pa": {"description": "Major axis position angle (North Eastwards)", "text": "40.4", "unit": "deg", "value": 40.4}, "t": {"description": "Morphological type code", "text": "0.3 ± 1.5", "unit": "", "value": [0.3, 1.5]}, "type": {"description": "Morphological type", "text": "S0-a", "unit": "", "value": "S0-a "}, "v": {"description": "Mean Heliocentric radial velocity (cz)", "text": "2443 ± 18", "unit": "km/s", "value": [2443, 18]}, "v3k": {"description": "Radial velocity (cz) with respect to the CMB radiation", "text": "2781 ± 18", "unit": "km/s", "value": [2781, 18]}, "vgsr": {"description": "Radial velocity (cz) with respect to the GSR", "text": "2327 ± 18", "unit": "km/s", "value": [2327, 18]}, "vlg": {"description": "Radial velocity (cz) with respect to the Local Group", "text": "2251 ± 18", "unit": "km/s", "value": [2251, 18]}, "vmaxg": {"description": "Apparent maximum rotation velocity of gas", "text": "84.1 ± 7.5", "unit": "km/s", "value": [84.1, 7.5]}, "vrot": {"description": "Maximum rotation velocity corrected for inclination", "text": "94.5 ± 8.5", "unit": "km/s", "value": [94.5, 8.5]}, "vvir": {"description": "Radial velocity (cz) corrected for LG infall onto Virgo", "text": "2442 ± 18", "unit": "km/s", "value": [2442, 18]}}}