{"aliases": ["2MASXJ15385172+1204498", "CGCG078-036", "IC1131", "MCG+02-40-008", "NPM1G+12.0438", "PGC055683", "SDSSJ153851.70+120450.2", "SDSSJ153851.70+120450.3", "UZC153630+12140"], "dec": ["+", "12", "04", "50.3"], "dec_float": 12.080638888888888, "name": "IC 1131", "ra": ["15", "38", "51.71"], "ra_float": 15.647697222222222, "values": {"a21": {"description": "21-cm self absorption", "text": "0.03", "unit": "mag", "value": 0.03}, "ag": {"description": "Galactic extinction in B-band", "text": "0.18", "unit": "mag", "value": 0.18}, "ai": {"description": "Internal extinction due to inclination in B-band", "text": "0.00", "unit": "mag", "value": 0.0}, "bri25": {"description": "Mean surface brightness within isophote 25 ", "text": "23.23", "unit": "mag/arcsec2", "value": 23.23}, "brief": {"description": "Mean effective surface brightness", "text": "21.46 ± 0.46", "unit": "mag/arcsec2", "value": [21.46, 0.46]}, "bt": {"description": "Total B-magnitude", "text": "14.73 ± 0.28", "unit": "mag", "value": [14.73, 0.28]}, "btc": {"description": "Total apparent corrected B-magnitude", "text": "14.52", "unit": "mag", "value": 14.52}, "grp_cz": {"description": "", "text": "2043.69", "unit": "", "value": 2043.69}, "grp_dec": {"description": "", "text": "13.76259", "unit": "", "value": 13.76259}, "grp_n": {"description": "", "text": "18", "unit": "", "value": 18.0}, "grp_ra": {"description": "", "text": "233.6226", "unit": "", "value": 233.6226}, "grp_rad": {"description": "", "text": "3.62201", "unit": "", "value": 3.62201}, "grp_sigma": {"description": "", "text": "188.938", "unit": "", "value": 188.938}, "incl": {"description": "Inclination between line of sight and polar axis of a galaxy", "text": "59.5", "unit": "deg", "value": 59.5}, "it": {"description": "Total I-magnitude", "text": "13.32 ± 0.05", "unit": "mag", "value": [13.32, 0.05]}, "itc": {"description": "Total apparent corrected I-magnitude", "text": "13.24", "unit": "mag", "value": 13.24}, "kt": {"description": "Total K-magnitude", "text": "11.10 ± 0.06", "unit": "mag", "value": [11.1, 0.06]}, "logd25": {"description": "log of apparent diameter (d25 in 0.1 arcmin)", "text": "0.93 ± 0.14", "unit": "log(0.1 arcmin)", "value": [0.93, 0.14]}, "logdc": {"description": "log of apparent corrected diameter (dc in 0.1 arcmin)", "text": "0.95", "unit": "log(0.1 arcmin)", "value": 0.95}, "logr25": {"description": "log of axis ratio (major axis/minor axis)", "text": "0.11 ± 0.06", "unit": "log", "value": [0.11, 0.06]}, "mabs": {"description": "Absolute B-band magnitude", "text": "-17.99 ± 0.573", "unit": "mag", "value": [-17.99, 0.573]}, "modbest": {"description": "Best distance modulus, combining mod0 and modz", "text": "32.51 ± 0.50", "unit": "mag", "value": [32.51, 0.5]}, "modz": {"description": "Cosmological distance modulus (from vvir with ΛCDM)", "text": "32.51 ± 0.50", "unit": "mag", "value": [32.51, 0.5]}, "objtype": {"description": "Type of object (G=galaxy; S=Star ...)", "text": "G", "unit": "", "value": "G  "}, "pa": {"description": "Major axis position angle (North Eastwards)", "text": "153.2", "unit": "deg", "value": 153.2}, "t": {"description": "Morphological type code", "text": "-4.8 ± 0.8", "unit": "", "value": [-4.8, 0.8]}, "type": {"description": "Morphological type", "text": "E", "unit": "", "value": "E    "}, "ut": {"description": "Total U-magnitude", "text": "15.85 ± 0.11", "unit": "mag", "value": [15.85, 0.11]}, "v": {"description": "Mean Heliocentric radial velocity (cz)", "text": "1980 ± 1", "unit": "km/s", "value": [1980, 1]}, "v3k": {"description": "Radial velocity (cz) with respect to the CMB radiation", "text": "2112 ± 1", "unit": "km/s", "value": [2112, 1]}, "vgsr": {"description": "Radial velocity (cz) with respect to the GSR", "text": "2045 ± 1", "unit": "km/s", "value": [2045, 1]}, "vlg": {"description": "Radial velocity (cz) with respect to the Local Group", "text": "2027 ± 1", "unit": "km/s", "value": [2027, 1]}, "vvir": {"description": "Radial velocity (cz) corrected for LG infall onto Virgo", "text": "2173 ± 1", "unit": "km/s", "value": [2173, 1]}}}