{"aliases": ["2MASXJ14183879+0722384", "CGCG047-001", "MCG+01-36-036", "NGC5549", "NIBLES2088", "PGC051118", "SDSSJ141838.81+072238.4", "SDSSJ141838.81+072238.5", "UGC09156", "UZC141606+07360"], "dec": ["+", "07", "22", "38.7"], "dec_float": 7.377416666666666, "name": "NGC 5549", "ra": ["14", "18", "38.82"], "ra_float": 14.310783333333333, "values": {"a21": {"description": "21-cm self absorption", "text": "0.11", "unit": "mag", "value": 0.11}, "ag": {"description": "Galactic extinction in B-band", "text": "0.13", "unit": "mag", "value": 0.13}, "ai": {"description": "Internal extinction due to inclination in B-band", "text": "0.00", "unit": "mag", "value": 0.0}, "bri25": {"description": "Mean surface brightness within isophote 25 ", "text": "23.57", "unit": "mag/arcsec2", "value": 23.57}, "brief": {"description": "Mean effective surface brightness", "text": "21.71 ± 0.19", "unit": "mag/arcsec2", "value": [21.71, 0.19]}, "bt": {"description": "Total B-magnitude", "text": "13.94 ± 0.38", "unit": "mag", "value": [13.94, 0.38]}, "btc": {"description": "Total apparent corrected B-magnitude", "text": "13.70", "unit": "mag", "value": 13.7}, "grp_cz": {"description": "", "text": "7527.1", "unit": "", "value": 7527.1}, "grp_dec": {"description": "", "text": "7.846213", "unit": "", "value": 7.846213}, "grp_n": {"description": "", "text": "99", "unit": "", "value": 99.0}, "grp_ra": {"description": "", "text": "213.6136", "unit": "", "value": 213.6136}, "grp_rad": {"description": "", "text": "2.0329", "unit": "", "value": 2.0329}, "grp_sigma": {"description": "", "text": "172.076", "unit": "", "value": 172.076}, "incl": {"description": "Inclination between line of sight and polar axis of a galaxy", "text": "81.2", "unit": "deg", "value": 81.2}, "it": {"description": "Total I-magnitude", "text": "11.97 ± 0.09", "unit": "mag", "value": [11.97, 0.09]}, "itc": {"description": "Total apparent corrected I-magnitude", "text": "11.91", "unit": "mag", "value": 11.91}, "kt": {"description": "Total K-magnitude", "text": "9.43 ± 0.05", "unit": "mag", "value": [9.43, 0.05]}, "logd25": {"description": "log of apparent diameter (d25 in 0.1 arcmin)", "text": "1.18 ± 0.04", "unit": "log(0.1 arcmin)", "value": [1.18, 0.04]}, "logdc": {"description": "log of apparent corrected diameter (dc in 0.1 arcmin)", "text": "1.19", "unit": "log(0.1 arcmin)", "value": 1.19}, "logr25": {"description": "log of axis ratio (major axis/minor axis)", "text": "0.31 ± 0.03", "unit": "log", "value": [0.31, 0.03]}, "mabs": {"description": "Absolute B-band magnitude", "text": "-21.59 ± 0.408", "unit": "mag", "value": [-21.59, 0.408]}, "modbest": {"description": "Best distance modulus, combining mod0 and modz", "text": "35.29 ± 0.14", "unit": "mag", "value": [35.29, 0.14]}, "modz": {"description": "Cosmological distance modulus (from vvir with ΛCDM)", "text": "35.29 ± 0.14", "unit": "mag", "value": [35.29, 0.14]}, "objtype": {"description": "Type of object (G=galaxy; S=Star ...)", "text": "G", "unit": "", "value": "G  "}, "pa": {"description": "Major axis position angle (North Eastwards)", "text": "118.9", "unit": "deg", "value": 118.9}, "t": {"description": "Morphological type code", "text": "-2.0 ± 0.4", "unit": "", "value": [-2.0, 0.4]}, "type": {"description": "Morphological type", "text": "S0", "unit": "", "value": "S0   "}, "ut": {"description": "Total U-magnitude", "text": "15.31 ± 0.01", "unit": "mag", "value": [15.31, 0.01]}, "v": {"description": "Mean Heliocentric radial velocity (cz)", "text": "7673 ± 3", "unit": "km/s", "value": [7673, 3]}, "v3k": {"description": "Radial velocity (cz) with respect to the CMB radiation", "text": "7916 ± 3", "unit": "km/s", "value": [7916, 3]}, "vgsr": {"description": "Radial velocity (cz) with respect to the GSR", "text": "7670 ± 3", "unit": "km/s", "value": [7670, 3]}, "vlg": {"description": "Radial velocity (cz) with respect to the Local Group", "text": "7628 ± 3", "unit": "km/s", "value": [7628, 3]}, "vvir": {"description": "Radial velocity (cz) corrected for LG infall onto Virgo", "text": "7814 ± 3", "unit": "km/s", "value": [7814, 3]}}}