{"aliases": ["2MASXJ15353688+5627424", "CGCG297-019", "MCG+09-26-002", "NGC5971", "PGC055529", "SDSSJ153536.89+562742.0", "SDSSJ153536.90+562742.0", "SDSSJ153536.90+562742.1", "SDSSJ153536.90+562742.3", "UGC09929", "UZC153424+56390"], "dec": ["+", "56", "27", "42.2"], "dec_float": 56.46172222222223, "name": "NGC 5971", "ra": ["15", "35", "36.92"], "ra_float": 15.59358888888889, "values": {"a21": {"description": "21-cm self absorption", "text": "0.06", "unit": "mag", "value": 0.06}, "ag": {"description": "Galactic extinction in B-band", "text": "0.04", "unit": "mag", "value": 0.04}, "ai": {"description": "Internal extinction due to inclination in B-band", "text": "0.32", "unit": "mag", "value": 0.32}, "bri25": {"description": "Mean surface brightness within isophote 25 ", "text": "23.56", "unit": "mag/arcsec2", "value": 23.56}, "brief": {"description": "Mean effective surface brightness", "text": "22.68 ± 0.63", "unit": "mag/arcsec2", "value": [22.68, 0.63]}, "bt": {"description": "Total B-magnitude", "text": "14.72 ± 0.32", "unit": "mag", "value": [14.72, 0.32]}, "btc": {"description": "Total apparent corrected B-magnitude", "text": "14.32", "unit": "mag", "value": 14.32}, "grp_cz": {"description": "", "text": "3549.66", "unit": "", "value": 3549.66}, "grp_dec": {"description": "", "text": "57.25029", "unit": "", "value": 57.25029}, "grp_n": {"description": "", "text": "40", "unit": "", "value": 40.0}, "grp_ra": {"description": "", "text": "233.2803", "unit": "", "value": 233.2803}, "grp_rad": {"description": "", "text": "2.75622", "unit": "", "value": 2.75622}, "grp_sigma": {"description": "", "text": "261.251", "unit": "", "value": 261.251}, "incl": {"description": "Inclination between line of sight and polar axis of a galaxy", "text": "73.2", "unit": "deg", "value": 73.2}, "it": {"description": "Total I-magnitude", "text": "13.13 ± 0.09", "unit": "mag", "value": [13.13, 0.09]}, "itc": {"description": "Total apparent corrected I-magnitude", "text": "13.11", "unit": "mag", "value": 13.11}, "kt": {"description": "Total K-magnitude", "text": "11.08 ± 0.12", "unit": "mag", "value": [11.08, 0.12]}, "logd25": {"description": "log of apparent diameter (d25 in 0.1 arcmin)", "text": "1.10 ± 0.05", "unit": "log(0.1 arcmin)", "value": [1.1, 0.05]}, "logdc": {"description": "log of apparent corrected diameter (dc in 0.1 arcmin)", "text": "1.09", "unit": "log(0.1 arcmin)", "value": 1.09}, "logr25": {"description": "log of axis ratio (major axis/minor axis)", "text": "0.37 ± 0.03", "unit": "log", "value": [0.37, 0.03]}, "mabs": {"description": "Absolute B-band magnitude", "text": "-19.32 ± 0.439", "unit": "mag", "value": [-19.32, 0.439]}, "modbest": {"description": "Best distance modulus, combining mod0 and modz", "text": "33.64 ± 0.30", "unit": "mag", "value": [33.64, 0.3]}, "modz": {"description": "Cosmological distance modulus (from vvir with ΛCDM)", "text": "33.64 ± 0.30", "unit": "mag", "value": [33.64, 0.3]}, "objtype": {"description": "Type of object (G=galaxy; S=Star ...)", "text": "G", "unit": "", "value": "G  "}, "pa": {"description": "Major axis position angle (North Eastwards)", "text": "132.2", "unit": "deg", "value": 132.2}, "ring": {"description": "Galaxy with ring (R)", "text": "R", "unit": "", "value": "R"}, "t": {"description": "Morphological type code", "text": "1.1 ± 0.5", "unit": "", "value": [1.1, 0.5]}, "type": {"description": "Morphological type", "text": "Sa", "unit": "", "value": "Sa   "}, "ut": {"description": "Total U-magnitude", "text": "15.74 ± 0.22", "unit": "mag", "value": [15.74, 0.22]}, "v": {"description": "Mean Heliocentric radial velocity (cz)", "text": "3364 ± 2", "unit": "km/s", "value": [3364, 2]}, "v3k": {"description": "Radial velocity (cz) with respect to the CMB radiation", "text": "3409 ± 2", "unit": "km/s", "value": [3409, 2]}, "vgsr": {"description": "Radial velocity (cz) with respect to the GSR", "text": "3522 ± 2", "unit": "km/s", "value": [3522, 2]}, "vlg": {"description": "Radial velocity (cz) with respect to the Local Group", "text": "3555 ± 2", "unit": "km/s", "value": [3555, 2]}, "vvir": {"description": "Radial velocity (cz) corrected for LG infall onto Virgo", "text": "3668 ± 2", "unit": "km/s", "value": [3668, 2]}}}